app/__init__.py
app/cli.py
app/core.py
app/exceptions.py
app/drivers/__init__.py
app/drivers/base.py
app/drivers/playwright_driver.py
app/drivers/selenium_driver.py
app/systems/__init__.py
app/systems/base.py
app/systems/ecac_system.py
app/systems/pje_system.py
whom_integration-1.0.2.dist-info/licenses/LICENSE
whom_integration-1.0.2.dist-info/METADATA
whom_integration-1.0.2.dist-info/WHEEL
whom_integration-1.0.2.dist-info/entry_points.txt
whom_integration-1.0.2.dist-info/top_level.txt
whom_integration-1.0.2.dist-info/RECORD
