Metadata-Version: 2.4
Name: whom-integration
Version: 1.0.2
Summary: Python library for Whom API integration, supporting multiple systems and web automation drivers
Home-page: https://github.com/doc9/whom-integration
Author: Doc9
Author-email: Doc9 <cloud@doc9.com.br>
Maintainer-email: Doc9 <cloud@doc9.com.br>
License-Expression: MIT
Project-URL: Homepage, https://github.com/doc9/whom-integration
Project-URL: Documentation, https://github.com/doc9/whom-integration#readme
Project-URL: Repository, https://github.com/doc9/whom-integration
Project-URL: Bug Tracker, https://github.com/doc9/whom-integration/issues
Project-URL: Changelog, https://github.com/doc9/whom-integration/blob/main/CHANGELOG.md
Keywords: whom,api,integration,automation,selenium,playwright,ecac,pje,receita-federal,judiciary,web-scraping,browser-automation
Classifier: Development Status :: 4 - Beta
Classifier: Intended Audience :: Developers
Classifier: Programming Language :: Python :: 3
Classifier: Topic :: Software Development :: Libraries :: Python Modules
Requires-Python: >=3.8
License-File: LICENSE
Requires-Dist: requests>=2.28.0
Requires-Dist: typing-extensions>=4.0.0
Provides-Extra: dev
Requires-Dist: pytest>=7.0.0; extra == "dev"
Requires-Dist: pytest-cov>=4.0.0; extra == "dev"
Requires-Dist: black>=22.0.0; extra == "dev"
Requires-Dist: flake8>=5.0.0; extra == "dev"
Requires-Dist: mypy>=1.0.0; extra == "dev"
Requires-Dist: pre-commit>=2.20.0; extra == "dev"
Requires-Dist: build>=0.10.0; extra == "dev"
Requires-Dist: twine>=4.0.0; extra == "dev"
Provides-Extra: selenium
Requires-Dist: selenium>=4.0.0; extra == "selenium"
Requires-Dist: webdriver-manager>=3.8.0; extra == "selenium"
Provides-Extra: playwright
Requires-Dist: playwright>=1.30.0; extra == "playwright"
Requires-Dist: patchright>=0.1.0; extra == "playwright"
Provides-Extra: all
Requires-Dist: selenium>=4.0.0; extra == "all"
Requires-Dist: webdriver-manager>=3.8.0; extra == "all"
Requires-Dist: playwright>=1.30.0; extra == "all"
Requires-Dist: patchright>=0.1.0; extra == "all"
Dynamic: author
Dynamic: home-page
Dynamic: license-file
Dynamic: requires-python
